unified_config/core/__init__.py
unified_config/core/config_manager.py
unified_config/core/data_conversion.py
unified_config/core/db_access.py
unified_config/core/db_operation.py
unified_config/core/logger.py
unified_config/core/schemas.py
unified_config/models/__init__.py
unified_config/models/db_model.py
unified_config-0.1.2.dist-info/LICENSE
unified_config-0.1.2.dist-info/METADATA
unified_config-0.1.2.dist-info/WHEEL
unified_config-0.1.2.dist-info/RECORD
