Metadata-Version: 2.1
Name: unified-config
Version: 0.1.2
Summary: A configuration manager library supporting YAML, JSON, and TOML with SQLAlchemy integration.
License: MIT
Author: yokha
Author-email: khaya.youssef@gmail.com
Requires-Python: >=3.8,<4.0
Classifier: License :: OSI Approved :: MIT License
Classifier: Programming Language :: Python :: 3
Classifier: Programming Language :: Python :: 3.8
Classifier: Programming Language :: Python :: 3.9
Classifier: Programming Language :: Python :: 3.10
Classifier: Programming Language :: Python :: 3.11
Classifier: Programming Language :: Python :: 3.12
Requires-Dist: PyYAML (>=6.0,<7.0)
Requires-Dist: asyncpg (>=0.30.0,<0.31.0)
Requires-Dist: fastapi (>=0.115.8,<0.116.0)
Requires-Dist: poetry (==1.8.0)
Requires-Dist: pydantic (>=2.0,<3.0)
Requires-Dist: redis-manager (>=0.1.1,<0.2.0)
Requires-Dist: sqlalchemy (>=2.0,<3.0)
Requires-Dist: toml (>=0.10.2,<0.11.0)
